README.rst
hentry.py
setup.py
hentry.egg-info/PKG-INFO
hentry.egg-info/SOURCES.txt
hentry.egg-info/dependency_links.txt
hentry.egg-info/not-zip-safe
hentry.egg-info/requires.txt
hentry.egg-info/top_level.txt