Metadata-Version: 1.1
Name: hentry
Version: 0.1
Summary: Parse hentry from microformats.
Home-page: https://github.com/lepture/hentry
Author: Hsiaoming Yang
Author-email: me@lepture.com
License: BSD
Platform: any
Classifier: Development Status :: 4 - Beta
Classifier: Environment :: Web Environment
Classifier: Intended Audience :: Developers
Classifier: License :: OSI Approved :: BSD License
Classifier: Operating System :: OS Independent
Classifier: Programming Language :: Python
Classifier: Topic :: Internet :: WWW/HTTP :: Dynamic Content
Classifier: Topic :: Software Development :: Libraries :: Python Modules
